{
    "/dist/App.js": "/dist/App.js?id=813d97d74590510b882d",
    "/dist/css/Global.css": "/dist/css/Global.css?id=f27156d200ffa53e4326",
    "/dist/css/StoreHome.css": "/dist/css/StoreHome.css?id=f220ee1487ccf5a5aea9",
    "/dist/css/StoreContentsListItem.css": "/dist/css/StoreContentsListItem.css?id=3b42e7c9a39ec819d3f9",
    "/dist/css/StoreDetailPage.css": "/dist/css/StoreDetailPage.css?id=077ef8d7c2d3f709ccc8",
    "/dist/css/StoreReviewList.css": "/dist/css/StoreReviewList.css?id=cd52c5e3fc3a1bf58185",
    "/dist/css/StoreReviewItem.css": "/dist/css/StoreReviewItem.css?id=5f1460eedc65cbda205c",
    "/dist/css/ReviewWritePage.css": "/dist/css/ReviewWritePage.css?id=2bd9bd199a338afed7f5",
    "/dist/css/StoreItemDetailPage.css": "/dist/css/StoreItemDetailPage.css?id=164d8a4a46b8f645a7b1",
    "/dist/css/StoreOrderPage.css": "/dist/css/StoreOrderPage.css?id=c366f6bfcabd83bb7ecd",
    "/dist/css/StoreOrderItem.css": "/dist/css/StoreOrderItem.css?id=28dfff8eea4e56236854",
    "/dist/css/StoreOrderComplitePage.css": "/dist/css/StoreOrderComplitePage.css?id=56a2597180fbd590eb09",
    "/dist/css/StoreReceiptItem.css": "/dist/css/StoreReceiptItem.css?id=394c64cb632dc821d63e",
    "/dist/css/StoreDetailReceipt.css": "/dist/css/StoreDetailReceipt.css?id=425b8299d93f5cb6c8f2",
    "/dist/css/MyContentsPage.css": "/dist/css/MyContentsPage.css?id=80329af84774add6a400",
    "/dist/css/StoreManager.css": "/dist/css/StoreManager.css?id=93f46034bd1e50133980",
    "/dist/css/StoreManagerTabAskOrderListPage.css": "/dist/css/StoreManagerTabAskOrderListPage.css?id=bc166fb5a920b4a7d60a",
    "/dist/App.js.map": "/dist/App.js.map?id=44087d745c32165663b1",
    "/dist/css/Global.css.map": "/dist/css/Global.css.map?id=5bbc1b2ffc8297fd13d5",
    "/dist/css/StoreHome.css.map": "/dist/css/StoreHome.css.map?id=90a9dbd291742064345e",
    "/dist/css/StoreContentsListItem.css.map": "/dist/css/StoreContentsListItem.css.map?id=d3b4320c51218ce209cb",
    "/dist/css/StoreDetailPage.css.map": "/dist/css/StoreDetailPage.css.map?id=d6750a92801506cbc7d6",
    "/dist/css/StoreReviewList.css.map": "/dist/css/StoreReviewList.css.map?id=f607b5863173b0b15aac",
    "/dist/css/StoreReviewItem.css.map": "/dist/css/StoreReviewItem.css.map?id=193aded432a57c316018",
    "/dist/css/ReviewWritePage.css.map": "/dist/css/ReviewWritePage.css.map?id=d67f4f58d6b467b25ec8",
    "/dist/css/StoreItemDetailPage.css.map": "/dist/css/StoreItemDetailPage.css.map?id=96fedc16b5ab081594ec",
    "/dist/css/StoreOrderPage.css.map": "/dist/css/StoreOrderPage.css.map?id=37f217b8310376dcbbba",
    "/dist/css/StoreOrderItem.css.map": "/dist/css/StoreOrderItem.css.map?id=446220ee9e60200526da",
    "/dist/css/StoreOrderComplitePage.css.map": "/dist/css/StoreOrderComplitePage.css.map?id=c54225432e11c311892d",
    "/dist/css/StoreReceiptItem.css.map": "/dist/css/StoreReceiptItem.css.map?id=7747ce5f5db11c9ac76c",
    "/dist/css/StoreDetailReceipt.css.map": "/dist/css/StoreDetailReceipt.css.map?id=d407a7bb56b95adfa9eb",
    "/dist/css/MyContentsPage.css.map": "/dist/css/MyContentsPage.css.map?id=75789e9e22723ad83a11",
    "/dist/css/StoreManager.css.map": "/dist/css/StoreManager.css.map?id=148a81eb7fd2e66c1ce5",
    "/dist/css/StoreManagerTabAskOrderListPage.css.map": "/dist/css/StoreManagerTabAskOrderListPage.css.map?id=3e694ac6295631b2f98a"
}
