{
    "/dist/App.js": "/dist/App.js?id=d1f3ef971e5f05b69a2d",
    "/dist/css/Global.css": "/dist/css/Global.css?id=6e055293139c71244c11",
    "/dist/css/StoreHome.css": "/dist/css/StoreHome.css?id=9e77702eda44cbede567",
    "/dist/css/StoreContentsListItem.css": "/dist/css/StoreContentsListItem.css?id=3f5e557f88f468ff247e",
    "/dist/css/StoreDetailPage.css": "/dist/css/StoreDetailPage.css?id=a258768133b792b8589e",
    "/dist/css/StoreReviewList.css": "/dist/css/StoreReviewList.css?id=cd52c5e3fc3a1bf58185",
    "/dist/css/StoreReviewItem.css": "/dist/css/StoreReviewItem.css?id=877ac217a6dc2caf50a1",
    "/dist/css/ReviewWritePage.css": "/dist/css/ReviewWritePage.css?id=2bd9bd199a338afed7f5",
    "/dist/css/StoreItemDetailPage.css": "/dist/css/StoreItemDetailPage.css?id=22c92fe87679e1c11dc7",
    "/dist/css/StoreOrderPage.css": "/dist/css/StoreOrderPage.css?id=52dc3e68e6b0d4c3b9f5",
    "/dist/css/StoreOrderItem.css": "/dist/css/StoreOrderItem.css?id=28dfff8eea4e56236854",
    "/dist/css/StoreOrderComplitePage.css": "/dist/css/StoreOrderComplitePage.css?id=56a2597180fbd590eb09",
    "/dist/css/StoreReceiptItem.css": "/dist/css/StoreReceiptItem.css?id=c15e8a2a054a8bd9dc02",
    "/dist/css/StoreDetailReceipt.css": "/dist/css/StoreDetailReceipt.css?id=425b8299d93f5cb6c8f2",
    "/dist/css/MyContentsPage.css": "/dist/css/MyContentsPage.css?id=80329af84774add6a400",
    "/dist/css/StoreManager.css": "/dist/css/StoreManager.css?id=0bbde8d0c14649cd03e7",
    "/dist/css/StoreManagerTabAskOrderListPage.css": "/dist/css/StoreManagerTabAskOrderListPage.css?id=795da51758eb6046038a",
    "/dist/css/FileUploader.css": "/dist/css/FileUploader.css?id=e3f27da29363bf17cb36",
    "/dist/css/StoreManagerTabStoreInfoPage.css": "/dist/css/StoreManagerTabStoreInfoPage.css?id=954880a1b41fbd1ef1b0",
    "/dist/css/StoreManagerTabItemPage.css": "/dist/css/StoreManagerTabItemPage.css?id=3569e159160ae52aa31c",
    "/dist/css/StoreAddItemPage.css": "/dist/css/StoreAddItemPage.css?id=89a81cf66aff281e9565",
    "/dist/css/StoreManagerTabOrderListPage.css": "/dist/css/StoreManagerTabOrderListPage.css?id=3bb1c33faaa6d07eac88",
    "/dist/css/StoreManagerTabAccountPage.css": "/dist/css/StoreManagerTabAccountPage.css?id=165500d871a6d0454886",
    "/dist/css/StoreUserSNSList.css": "/dist/css/StoreUserSNSList.css?id=25ec7e6f00a429386912",
    "/dist/css/StoreHomeStoreListItem.css": "/dist/css/StoreHomeStoreListItem.css?id=907a995df2b8b8c37e45",
    "/dist/css/Popup_progress.css": "/dist/css/Popup_progress.css?id=d5aa38dc278a46bb3893",
    "/dist/css/Popup_image_preview.css": "/dist/css/Popup_image_preview.css?id=ca36cd487def4ecd5ac4",
    "/dist/css/Popup_text_editor.css": "/dist/css/Popup_text_editor.css?id=48a39948f017140c4eed",
    "/dist/css/StoreContentConfirm.css": "/dist/css/StoreContentConfirm.css?id=92358b758b54f64c22c4",
    "/dist/css/Popup_text_viewer.css": "/dist/css/Popup_text_viewer.css?id=15ba5c6f29a72df9516a",
    "/dist/App.js.map": "/dist/App.js.map?id=1f0cf701754745f88eae",
    "/dist/css/Global.css.map": "/dist/css/Global.css.map?id=54e55fa75bede1265500",
    "/dist/css/StoreHome.css.map": "/dist/css/StoreHome.css.map?id=d04961009a034d0d581e",
    "/dist/css/StoreContentsListItem.css.map": "/dist/css/StoreContentsListItem.css.map?id=91621c217fdaba29ecf2",
    "/dist/css/StoreDetailPage.css.map": "/dist/css/StoreDetailPage.css.map?id=2a23af075df31db38408",
    "/dist/css/StoreReviewList.css.map": "/dist/css/StoreReviewList.css.map?id=f607b5863173b0b15aac",
    "/dist/css/StoreReviewItem.css.map": "/dist/css/StoreReviewItem.css.map?id=51fb1b8cb144698476c8",
    "/dist/css/ReviewWritePage.css.map": "/dist/css/ReviewWritePage.css.map?id=d67f4f58d6b467b25ec8",
    "/dist/css/StoreItemDetailPage.css.map": "/dist/css/StoreItemDetailPage.css.map?id=dc23c74a831048cad53e",
    "/dist/css/StoreOrderPage.css.map": "/dist/css/StoreOrderPage.css.map?id=2e32bddb874ec2e16b7c",
    "/dist/css/StoreOrderItem.css.map": "/dist/css/StoreOrderItem.css.map?id=446220ee9e60200526da",
    "/dist/css/StoreOrderComplitePage.css.map": "/dist/css/StoreOrderComplitePage.css.map?id=c54225432e11c311892d",
    "/dist/css/StoreReceiptItem.css.map": "/dist/css/StoreReceiptItem.css.map?id=5b4a9d7a48a8cdbcdec9",
    "/dist/css/StoreDetailReceipt.css.map": "/dist/css/StoreDetailReceipt.css.map?id=d407a7bb56b95adfa9eb",
    "/dist/css/MyContentsPage.css.map": "/dist/css/MyContentsPage.css.map?id=75789e9e22723ad83a11",
    "/dist/css/StoreManager.css.map": "/dist/css/StoreManager.css.map?id=6b43c38428b0505f12f2",
    "/dist/css/StoreManagerTabAskOrderListPage.css.map": "/dist/css/StoreManagerTabAskOrderListPage.css.map?id=19dd558151080f0c1dbe",
    "/dist/css/FileUploader.css.map": "/dist/css/FileUploader.css.map?id=7211c7ee94b9cdb8550e",
    "/dist/css/StoreManagerTabStoreInfoPage.css.map": "/dist/css/StoreManagerTabStoreInfoPage.css.map?id=5147e48d632ac28c3987",
    "/dist/css/StoreManagerTabItemPage.css.map": "/dist/css/StoreManagerTabItemPage.css.map?id=0976e931250e049781ce",
    "/dist/css/StoreAddItemPage.css.map": "/dist/css/StoreAddItemPage.css.map?id=947d301614cdbc90bc98",
    "/dist/css/StoreManagerTabOrderListPage.css.map": "/dist/css/StoreManagerTabOrderListPage.css.map?id=2c6cd3d5ebe2b4dd3be3",
    "/dist/css/StoreManagerTabAccountPage.css.map": "/dist/css/StoreManagerTabAccountPage.css.map?id=3bfa78b6d05b3beae274",
    "/dist/css/StoreUserSNSList.css.map": "/dist/css/StoreUserSNSList.css.map?id=0f77b37ce3d801fb6dd9",
    "/dist/css/StoreHomeStoreListItem.css.map": "/dist/css/StoreHomeStoreListItem.css.map?id=9446ba4fa8c0a8174df8",
    "/dist/css/Popup_progress.css.map": "/dist/css/Popup_progress.css.map?id=b5811020c74535b45fd2",
    "/dist/css/Popup_image_preview.css.map": "/dist/css/Popup_image_preview.css.map?id=f8853034c708eb7b5e10",
    "/dist/css/Popup_text_editor.css.map": "/dist/css/Popup_text_editor.css.map?id=b0ea107533303e81b018",
    "/dist/css/StoreContentConfirm.css.map": "/dist/css/StoreContentConfirm.css.map?id=3bad136a8a29cbc5e350",
    "/dist/css/Popup_text_viewer.css.map": "/dist/css/Popup_text_viewer.css.map?id=df49889e3936a58b7eb6"
}
